photomap/__init__.py
photomap/backend/__init__.py
photomap/backend/args.py
photomap/backend/config.py
photomap/backend/constants.py
photomap/backend/embeddings.py
photomap/backend/imagetool.py
photomap/backend/metadata_extraction.py
photomap/backend/metadata_formatting.py
photomap/backend/photomap_server.py
photomap/backend/progress.py
photomap/backend/util.py
photomap/backend/metadata_modules/__init__.py
photomap/backend/metadata_modules/exif_formatter.py
photomap/backend/metadata_modules/invoke_formatter.py
photomap/backend/metadata_modules/slide_summary.py
photomap/backend/metadata_modules/invoke/__init__.py
photomap/backend/metadata_modules/invoke/invoke_metadata_abc.py
photomap/backend/metadata_modules/invoke/legacy.py
photomap/backend/metadata_modules/invoke/v3.py
photomap/backend/metadata_modules/invoke/v5.py
photomap/backend/routers/__init__.py
photomap/backend/routers/album.py
photomap/backend/routers/curation.py
photomap/backend/routers/filetree.py
photomap/backend/routers/index.py
photomap/backend/routers/search.py
photomap/backend/routers/umap.py
photomap/backend/routers/upgrade.py
photomap/frontend/__init__.py
photomap/frontend/static/main.js
photomap/frontend/static/css/about.css
photomap/frontend/static/css/album-manager.css
photomap/frontend/static/css/animations.css
photomap/frontend/static/css/base.css
photomap/frontend/static/css/bookmarks.css
photomap/frontend/static/css/control-and-search-panels.css
photomap/frontend/static/css/curation.css
photomap/frontend/static/css/delete-modal.css
photomap/frontend/static/css/filetree.css
photomap/frontend/static/css/grid-view.css
photomap/frontend/static/css/metadata-drawer.css
photomap/frontend/static/css/modal-base.css
photomap/frontend/static/css/search.css
photomap/frontend/static/css/seek-slider.css
photomap/frontend/static/css/settings.css
photomap/frontend/static/css/spinners.css
photomap/frontend/static/css/swiper.css
photomap/frontend/static/css/umap-floating-window.css
photomapai-1.0.3.dist-info/licenses/LICENSE
photomapai-1.0.3.dist-info/METADATA
photomapai-1.0.3.dist-info/WHEEL
photomapai-1.0.3.dist-info/entry_points.txt
photomapai-1.0.3.dist-info/top_level.txt
photomapai-1.0.3.dist-info/RECORD
