Metadata-Version: 2.4
Name: photomapai
Version: 1.0.3
Summary: AI-based image clustering and exploration tool
Author-email: Lincoln Stein <lincoln.stein@gmail.com>
License: MIT
Project-URL: Homepage, https://github.com/lstein/PhotoMapAI
Classifier: Development Status :: 4 - Beta
Classifier: Intended Audience :: End Users/Desktop
Classifier: Intended Audience :: Developers
Classifier: Programming Language :: Python :: 3.10
Classifier: Programming Language :: Python :: 3.11
Classifier: Programming Language :: Python :: 3.12
Classifier: Programming Language :: Python :: 3.13
Classifier: Topic :: Multimedia :: Graphics :: Viewers
Classifier: Topic :: Software Development :: Libraries :: Application Frameworks
Classifier: Topic :: Software Development :: Libraries :: Python Modules
Requires-Python: <3.14,>=3.10
License-File: LICENSE
Requires-Dist: Pillow
Requires-Dist: clip-anytorch
Requires-Dist: colorama
Requires-Dist: dash
Requires-Dist: fastapi
Requires-Dist: jinja2
Requires-Dist: networkx
Requires-Dist: numpy
Requires-Dist: pandas
Requires-Dist: pillow-heif
Requires-Dist: platformdirs
Requires-Dist: pydantic
Requires-Dist: python-multipart
Requires-Dist: PyYAML
Requires-Dist: requests
Requires-Dist: scikit-learn
Requires-Dist: setuptools<67
Requires-Dist: torch
Requires-Dist: tqdm
Requires-Dist: umap-learn
Requires-Dist: uvicorn
Requires-Dist: psutil
Requires-Dist: packaging
Provides-Extra: testing
Requires-Dist: pytest; extra == "testing"
Requires-Dist: pytest-cov; extra == "testing"
Requires-Dist: httpx; extra == "testing"
Requires-Dist: asynctest; extra == "testing"
Requires-Dist: pytest-asyncio; extra == "testing"
Provides-Extra: development
Requires-Dist: build; extra == "development"
Requires-Dist: mkdocs-material; extra == "development"
Requires-Dist: twine; extra == "development"
Requires-Dist: pymdown-extensions; extra == "development"
Requires-Dist: pyinstaller; extra == "development"
Requires-Dist: ruff; extra == "development"
Dynamic: license-file
